AgentRL/__init__.py
AgentRL/agents/__init__.py
AgentRL/agents/base.py
AgentRL/agents/deep_q_network.py
AgentRL/common/__init__.py
AgentRL/common/buffers/__init__.py
AgentRL/common/buffers/base.py
AgentRL/common/buffers/prioritised_buffer.py
AgentRL/common/buffers/standard_buffer.py
AgentRL/common/exploration/__init__.py
AgentRL/common/exploration/argmax.py
AgentRL/common/exploration/base.py
AgentRL/common/exploration/e_greedy.py
AgentRL/common/layers/__init__.py
AgentRL/common/layers/custom_layers.py
AgentRL/common/policy_networks/__init__.py
AgentRL/common/value_networks/__init__.py
AgentRL/common/value_networks/base.py
AgentRL/common/value_networks/standard_value_net.py
AgentRL-0.0.18.dist-info/LICENSE
AgentRL-0.0.18.dist-info/METADATA
AgentRL-0.0.18.dist-info/WHEEL
AgentRL-0.0.18.dist-info/top_level.txt
AgentRL-0.0.18.dist-info/RECORD
