Metadata-Version: 2.1
Name: AgentRL
Version: 0.0.18
Summary: AgentRL
Home-page: UNKNOWN
Author: Harry Emerson
Author-email: emersonharry8@gmail.com
License: UNKNOWN
Keywords: reinforcement learning,agent
Platform: UNKNOWN
Classifier: Development Status :: 3 - Alpha
Classifier: Intended Audience :: Education
Classifier: Programming Language :: Python :: 2
Classifier: Programming Language :: Python :: 3
Classifier: Operating System :: MacOS :: MacOS X
Classifier: Operating System :: Microsoft :: Windows
Requires-Dist: numpy (>=1.21.4)
Requires-Dist: setuptools (>=58.0.4)
Requires-Dist: torch (>=1.10.0)
